README
setup.py
src/geogig_py.egg-info/PKG-INFO
src/geogig_py.egg-info/SOURCES.txt
src/geogig_py.egg-info/dependency_links.txt
src/geogig_py.egg-info/requires.txt
src/geogig_py.egg-info/top_level.txt
src/geogigpy/__init__.py
src/geogigpy/cliconnector.py
src/geogigpy/commit.py
src/geogigpy/commitish.py
src/geogigpy/connector.py
src/geogigpy/diff.py
src/geogigpy/examples.py
src/geogigpy/feature.py
src/geogigpy/geogig.py
src/geogigpy/geogigexception.py
src/geogigpy/geogigserverconnector.py
src/geogigpy/geometry.py
src/geogigpy/osmmapping.py
src/geogigpy/py4jconnector.py
src/geogigpy/repo.py
src/geogigpy/tree.py
src/geogigpy/utils.py