Metadata-Version: 1.1
Name: geogig-py
Version: 1.0
Summary: Python bindings for GeoGig
Home-page: https://github.com/boundlessgeo/geogig-py
Author: Victor Olaya
Author-email: volaya@boundlessgeo.com
License: BSD
Keywords: geogig
Platform: UNKNOWN
Classifier: Development Status :: 4 - Beta
